nopii/__init__.py
nopii/cli/__init__.py
nopii/cli/main.py
nopii/cli/utils.py
nopii/cli/commands/__init__.py
nopii/cli/commands/diff.py
nopii/cli/commands/policy.py
nopii/cli/commands/report.py
nopii/cli/commands/scan.py
nopii/cli/commands/transform.py
nopii/core/__init__.py
nopii/core/models.py
nopii/core/scanner.py
nopii/core/transform.py
nopii/detectors/__init__.py
nopii/detectors/base.py
nopii/detectors/credit_card.py
nopii/detectors/email.py
nopii/detectors/patterns.py
nopii/detectors/phone.py
nopii/detectors/registry.py
nopii/detectors/ssn.py
nopii/policy/__init__.py
nopii/policy/loader.py
nopii/policy/models.py
nopii/policy/validator.py
nopii/reporting/__init__.py
nopii/reporting/coverage.py
nopii/reporting/generators.py
nopii/reporting/templates.py
nopii/sdk/__init__.py
nopii/sdk/client.py
nopii/sdk/policy.py
nopii/sdk/scanner.py
nopii/sdk/transform.py
nopii/transforms/__init__.py
nopii/transforms/base.py
nopii/transforms/hash.py
nopii/transforms/mask.py
nopii/transforms/nullify.py
nopii/transforms/redact.py
nopii/transforms/registry.py
nopii/transforms/tokenize.py
nopii-0.1.3.dist-info/licenses/LICENSE
nopii-0.1.3.dist-info/METADATA
nopii-0.1.3.dist-info/WHEEL
nopii-0.1.3.dist-info/entry_points.txt
nopii-0.1.3.dist-info/top_level.txt
nopii-0.1.3.dist-info/RECORD
