Metadata-Version: 2.4
Name: nopii
Version: 0.1.3
Summary: A batteries-included Python toolkit for detecting, transforming, masking, pseudonymizing, and auditing PII across data engineering workflows
Author: ay-mich
License-Expression: Apache-2.0
Project-URL: Homepage, https://github.com/ay-mich/nopii
Project-URL: Documentation, https://ay-mich.github.io/nopii/nopii.html
Project-URL: Repository, https://github.com/ay-mich/nopii
Project-URL: Issues, https://github.com/ay-mich/nopii/issues
Keywords: pii,privacy,data-protection,transformation,compliance,gdpr,ccpa
Classifier: Development Status :: 4 - Beta
Classifier: Intended Audience :: Developers
Classifier: Programming Language :: Python :: 3
Classifier: Programming Language :: Python :: 3.12
Classifier: Topic :: Security
Classifier: Topic :: Software Development :: Libraries :: Python Modules
Classifier: Topic :: Scientific/Engineering :: Information Analysis
Requires-Python: >=3.12
License-File: LICENSE
Requires-Dist: click>=8.0.0
Requires-Dist: pyyaml>=6.0
Requires-Dist: pydantic>=2.0.0
Requires-Dist: jinja2>=3.0.0
Requires-Dist: rich>=13.0.0
Requires-Dist: typing-extensions>=4.5.0
Provides-Extra: pandas
Requires-Dist: pandas>=2.0.0; extra == "pandas"
Requires-Dist: numpy>=1.24.0; extra == "pandas"
Provides-Extra: report-html
Requires-Dist: plotly>=5.0.0; extra == "report-html"
Requires-Dist: kaleido>=0.2.1; extra == "report-html"
Requires-Dist: weasyprint>=59.0; extra == "report-html"
Provides-Extra: dev
Requires-Dist: pytest>=7.0.0; extra == "dev"
Requires-Dist: pytest-cov>=4.0.0; extra == "dev"
Requires-Dist: pytest-asyncio>=0.21.0; extra == "dev"
Requires-Dist: pytest-mock>=3.11.0; extra == "dev"
Requires-Dist: mypy>=1.5.0; extra == "dev"
Requires-Dist: pre-commit>=3.0.0; extra == "dev"
Requires-Dist: ruff>=0.0.280; extra == "dev"
Requires-Dist: bandit>=1.7.5; extra == "dev"
Requires-Dist: vulture>=2.14; extra == "dev"
Requires-Dist: twine>=6.2.0; extra == "dev"
Requires-Dist: pip-audit>=2.9.0; extra == "dev"
Dynamic: license-file
